hanary_mcp/__init__.py
hanary_mcp/client.py
hanary_mcp/init.py
hanary_mcp/server.py
hanary_mcp-0.14.1.dist-info/METADATA
hanary_mcp-0.14.1.dist-info/WHEEL
hanary_mcp-0.14.1.dist-info/entry_points.txt
hanary_mcp-0.14.1.dist-info/RECORD
