Metadata-Version: 2.4
Name: hanary-mcp
Version: 0.14.1
Summary: Hanary MCP Server - Task management for Claude Code, OpenCode & OpenAI Codex
Author: Hanary
License: MIT
Keywords: claude,codex,hanary,mcp,openai,task-management
Classifier: Development Status :: 3 - Alpha
Classifier: Intended Audience :: Developers
Classifier: License :: OSI Approved :: MIT License
Classifier: Programming Language :: Python :: 3
Classifier: Programming Language :: Python :: 3.10
Classifier: Programming Language :: Python :: 3.11
Classifier: Programming Language :: Python :: 3.12
Requires-Python: >=3.10
Requires-Dist: mcp>=1.0.0
Requires-Dist: requests>=2.32.5
